cobib/__init__.py
cobib/__main__.py
cobib/py.typed
cobib/commands/__init__.py
cobib/commands/add.py
cobib/commands/base_command.py
cobib/commands/delete.py
cobib/commands/edit.py
cobib/commands/export.py
cobib/commands/git.py
cobib/commands/import_.py
cobib/commands/init.py
cobib/commands/lint.py
cobib/commands/list_.py
cobib/commands/man.py
cobib/commands/modify.py
cobib/commands/note.py
cobib/commands/open.py
cobib/commands/redo.py
cobib/commands/review.py
cobib/commands/search.py
cobib/commands/show.py
cobib/commands/tutorial.py
cobib/commands/undo.py
cobib/commands/unify_labels.py
cobib/config/__init__.py
cobib/config/command.py
cobib/config/config.py
cobib/config/event.py
cobib/config/example.py
cobib/database/__init__.py
cobib/database/author.py
cobib/database/database.py
cobib/database/entry.py
cobib/exporters/__init__.py
cobib/exporters/base_exporter.py
cobib/exporters/bibtex.py
cobib/exporters/yaml.py
cobib/exporters/zip.py
cobib/importers/__init__.py
cobib/importers/base_importer.py
cobib/importers/bibtex.py
cobib/importers/yaml.py
cobib/man/__init__.py
cobib/man/manual.py
cobib/parsers/__init__.py
cobib/parsers/arxiv.py
cobib/parsers/base_parser.py
cobib/parsers/bibtex.py
cobib/parsers/doi.py
cobib/parsers/isbn.py
cobib/parsers/url.py
cobib/parsers/yaml.py
cobib/ui/__init__.py
cobib/ui/cli.py
cobib/ui/shell.py
cobib/ui/tui.py
cobib/ui/ui.py
cobib/ui/components/__init__.py
cobib/ui/components/entry_view.py
cobib/ui/components/input_screen.py
cobib/ui/components/list_view.py
cobib/ui/components/log_screen.py
cobib/ui/components/main_content.py
cobib/ui/components/manual_screen.py
cobib/ui/components/motion_key.py
cobib/ui/components/note_view.py
cobib/ui/components/preset_filter_screen.py
cobib/ui/components/search_view.py
cobib/ui/components/selection_filter.py
cobib/utils/__init__.py
cobib/utils/console.py
cobib/utils/context.py
cobib/utils/diff_renderer.py
cobib/utils/file_downloader.py
cobib/utils/git.py
cobib/utils/journal_abbreviations.py
cobib-6.0.0.dist-info/licenses/LICENSE.txt
cobib-6.0.0.dist-info/METADATA
cobib-6.0.0.dist-info/WHEEL
cobib-6.0.0.dist-info/entry_points.txt
cobib-6.0.0.dist-info/top_level.txt
cobib-6.0.0.dist-info/RECORD
