Metadata-Version: 2.4
Name: cobib
Version: 6.0.0
Summary: Console Bibliography
Author-email: Max Rossmannek <max@rossmannek.de>
License-Expression: MIT
Project-URL: Homepage, https://gitlab.com/cobib/cobib
Project-URL: Documentation, https://cobib.gitlab.io/cobib/cobib.html
Project-URL: Repository, https://gitlab.com/cobib/cobib
Project-URL: Issues, https://gitlab.com/cobib/cobib/-/issues
Project-URL: Changelog, https://gitlab.com/cobib/cobib/-/blob/master/CHANGELOG.md
Keywords: reference-manager,citation-manager,bibliography,cli,tui,command-line,terminal,console,bibtex,doi,arxiv,isbn
Classifier: Programming Language :: Python :: 3
Classifier: Programming Language :: Python :: 3.10
Classifier: Programming Language :: Python :: 3.11
Classifier: Programming Language :: Python :: 3.12
Classifier: Programming Language :: Python :: 3.13
Classifier: Programming Language :: Python :: 3.14
Classifier: Operating System :: Unix
Classifier: Environment :: Console
Classifier: Typing :: Typed
Requires-Python: >=3.10
License-File: LICENSE.txt
Requires-Dist: beautifulsoup4
Requires-Dist: bibtexparser<2
Requires-Dist: lxml
Requires-Dist: natsort
Requires-Dist: pylatexenc
Requires-Dist: requests
Requires-Dist: requests_oauthlib
Requires-Dist: rich
Requires-Dist: ruamel.yaml
Requires-Dist: text-unidecode
Requires-Dist: textual>=2.0
Requires-Dist: typing_extensions
Provides-Extra: all
Requires-Dist: cobib[cyaml,fuzzy,shell]; extra == "all"
Provides-Extra: cyaml
Requires-Dist: ruamel.yaml.clib; extra == "cyaml"
Provides-Extra: fuzzy
Requires-Dist: regex; extra == "fuzzy"
Provides-Extra: shell
Requires-Dist: prompt_toolkit; extra == "shell"
Provides-Extra: dev
Requires-Dist: cobib[coverage,docs,lint]; extra == "dev"
Provides-Extra: basedev
Requires-Dist: pytest~=8.4.1; extra == "basedev"
Provides-Extra: docs
Requires-Dist: cobib[basedev]; extra == "docs"
Requires-Dist: pdoc~=15.0.4; extra == "docs"
Requires-Dist: textual-dev~=1.8.0; extra == "docs"
Provides-Extra: test
Requires-Dist: cobib[basedev]; extra == "test"
Requires-Dist: pytest-asyncio~=1.2.0; extra == "test"
Requires-Dist: pytest-textual-snapshot~=1.1.0; extra == "test"
Requires-Dist: ruamel.yaml.clib; extra == "test"
Requires-Dist: textual>=6.0; extra == "test"
Provides-Extra: coverage
Requires-Dist: cobib[test]; extra == "coverage"
Requires-Dist: coverage~=7.10.6; extra == "coverage"
Requires-Dist: pytest-cov~=7.0.0; extra == "coverage"
Provides-Extra: lint
Requires-Dist: cobib[basedev]; extra == "lint"
Requires-Dist: mypy~=1.18.1; extra == "lint"
Requires-Dist: ruff~=0.14.0; extra == "lint"
Requires-Dist: types-beautifulsoup4==4.12.0.20250516; extra == "lint"
Requires-Dist: types-regex==2025.9.18.20250921; extra == "lint"
Requires-Dist: types-requests-oauthlib==2.0.0.20250809; extra == "lint"
Requires-Dist: types-requests==2.32.4.20250913; extra == "lint"
Requires-Dist: typos~=1.38.1; extra == "lint"
Dynamic: license-file
